{"id":"308560","vid":"11907","title":"杀手3","sub":"HITMAN 3","length":6,"score":9.6,"count":86,"platform":[{"label":"XSX|S","cn":false},{"label":"PS5","cn":false},{"label":"NS","cn":false},{"label":"PS4","cn":false},{"label":"XB1","cn":false},{"label":"PC","cn":false}],"date":[["最早发售 2021-01-20"],["最早发售 2021-01-20"],["最早发售 2021-01-20"],["最早发售 2021-01-20"],["最早发售 2021-01-20"],["最早发售 2021-01-20"],["最早发售 2021-01-20"]],"tags":["动作","第三人称","潜入"],"desc":"《杀手3》将是“杀手”系列三部曲的最终作。本作将继续《杀手2》的故事线，因此《杀手2》的玩家可以在新作中直接导入位置和存档数据，并且还能够导入前两作的地图。该作全程支持使用 PS VR 游玩。","dev":["IO Interactive"],"pub":["IO Interactive"]}