{"id":"216897","vid":"3519","title":"蔽日灰烬","sub":"Ashen","length":9,"score":7.7,"count":48,"platform":[{"label":"NS","cn":true},{"label":"PS4","cn":true},{"label":"XB1","cn":true},{"label":"PC","cn":true}],"date":[["最早发售 2019-12-09","中文发售 2019-12-09"],["最早发售 2019-12-09","中文发售 2019-12-09"],["最早发售 2018-12-07","中文发售 2018-12-07"],["最早发售 2018-12-07","中文发售 2018-12-07"],["最早发售 2018-12-07","中文发售 2018-12-07"]],"tags":["动作","角色扮演","冒险"],"desc":"本作是一款动作角色扮演游戏，玩家所扮演的角色的星球遭受了巨大的火山灾难，玩家时其中为数不多的幸存者之一。灾难之下，这个星球上的火山灰遮天蔽日，很难以后什么能够存活下来，而游戏的目的是要玩家找到一个安身之所。在游戏中玩家会随机地遇到其他玩家，但他们也有着自己的行程和打算。当然你需要其他人的帮助，但如何与他们相处则取决于你自己。","lang":["简中"],"dev":["Aurora44"],"pub":["Annapurna Interactive"]}