{"id":"19884","vid":"2769","title":"尘埃3","sub":"Dirt 3","length":11,"score":8.2,"count":83,"platform":[{"label":"PS3","cn":false},{"label":"X360","cn":false}],"date":["最早发售 2011-05-24"],"tags":["竞速"],"desc":"作为主机版拉力竞速游戏系列最新作，画面上的进化并不明显，但是游戏的手感有一定的改变。前作主题是极限运动，本作在极限运动的基础上延展出花式技巧，并以场地特技为中心添加了定点漂移、高跳、甜甜圈等刺激的特技动作，加上世界级极限运动明星Ken Block的倾力支持，本作在趣味性和收藏价值上都达到了系列的新高度。不过倒是竞速本身的核心性有所降低，压线、甩尾、与离心力抗衡一路尘土飞扬力争第一个到达终点的模式和展示特技的模式并肩同行。在线模式有大幅强化，火爆的同场竞技会和好友之间擦出靓丽火花，新加入的驾驶车辆夺旗、感染病毒等趣味竞赛也值得尝试。","dev":["Codemasters"],"pub":["Codemasters"]}