{"id":"89516","vid":"609","title":"洞穴探险","sub":"Spelunky","length":11,"score":7.4,"count":45,"platform":[{"label":"NS","cn":false},{"label":"PS4","cn":false},{"label":"PC","cn":false},{"label":"PSV","cn":false},{"label":"PS3","cn":false},{"label":"X360","cn":false}],"date":[["最早发售 2021-夏季"],["最早发售 2014-10-07"],["最早发售 2013-08-08"],["最早发售 2013-08-27"],["最早发售 2013-08-27"],["最早发售 2012-07-04"],["最早发售 2012-07-04"]],"tags":["动作","平台","冒险"],"desc":"一款横版动作游戏，主题是在地底挖掘钻探，寻找宝藏，目标是获得最多的美元。游戏关卡随机生成，玩家每次死亡之后，面对的都是一个全新的局面，重复可玩性满点。本作的道具武器种类繁多，恰当使用才能在洞穴中尽可能长时间地生存。同时本作也支持多人合作游玩。","dev":["Mossmouth"],"pub":["Mossmouth"]}