{"id":"312236","vid":"12205","title":"绿林侠盗：亡命之徒与传奇","sub":"Hood: Outlaws & Legends","length":8,"score":9.3,"count":32,"platform":[{"label":"XSX|S","cn":true},{"label":"PS5","cn":true},{"label":"PS4","cn":true},{"label":"XB1","cn":true},{"label":"PC","cn":true}],"date":[["最早发售 2021-05-10","中文发售 2021-05-10"],["最早发售 2021-05-10","中文发售 2021-05-10"],["最早发售 2021-05-10","中文发售 2021-05-10"],["最早发售 2021-05-10","中文发售 2021-05-10"],["最早发售 2021-05-11","中文发售 2021-05-11"],["最早发售 2021-05-10","中文发售 2021-05-10"]],"tags":["动作","角色扮演","冒险","潜入"],"desc":"本作是一款中世纪风格的多人动作游戏，玩家将分为两个小组，分别发挥不同角色的独特技能和神秘能力，在严密巡逻守卫的环境中隐身潜入盗取宝藏。据官方介绍，游戏将在发售后不断增加全新地图以及更丰富的玩法，相信会给玩家带来新奇刺激的潜入体验。对于潜入玩法及中世纪风格情有独钟的玩家千万不要错过。","lang":["简中"],"dev":["Sumo Digital"],"pub":["Focus Home Interactive"]}