{"id":"334272","vid":"12314","title":"质量效应 传奇版","sub":"Mass Effect Legendary Edition","length":7,"score":9.7,"count":37,"platform":[{"label":"XSX|S","cn":false},{"label":"PS5","cn":false},{"label":"PS4","cn":false},{"label":"XB1","cn":false},{"label":"PC","cn":false}],"date":[["最早发售 2021-05-14"],["最早发售 2021-05-14"],["最早发售 2021-05-14"],["最早发售 2021-05-14"],["最早发售 2021-05-14"],["最早发售 2021-05-14"]],"tags":["动作","角色扮演","科幻","射击"],"desc":"本作是科幻动作射击游戏《质量效应》系列的高清复刻合集，游戏包含原版单人模式 DLC 等内容，游戏画面将强化至 4K 超高清。除登陆本世代主机外，本作还会通过“向上兼容”的方式在次世代主机上运行。","dev":["BioWare"],"pub":["EA"]}