{"id":"13369","vid":"2534","title":"闪电十一人2 威胁的侵略者","sub":"イナズマイレブン2 脅威の侵略者 ファイア","length":4,"score":0,"count":0,"platform":[{"label":"NDS","cn":false}],"date":["最早发售 2009-10-01"],"tags":["角色扮演"],"desc":"大受好评足球题材角色扮演游戏的第二部作品，游戏以特殊的视角描写了一群热血少年为了心爱的足球而奋斗的故事。本作的剧情紧接前作，但是雷门中学与元堂守的对手换成了想要侵占地球的穷凶极恶的外星人。本作游戏的舞台更加宽广，玩家可以带领自己的球队征战日本全国，玩家将走访日本各地一边追寻外星球队一边邀请其他足球高手加盟，日本各地的美丽风景将全部展现在玩家面前。游戏的一大特色就是收集同伴，本作为玩家准备了超过1500名能力各异的同伴，而且每个同伴的性格极具特色，就连前日本国家队的球员中田英寿也会作为隐藏同伴登场。各种必杀技演出效果比前作更为华丽，而且敌队阵营中的角色还会使用与众不同的必杀技。","dev":["LEVEL-5"],"pub":["LEVEL-5"]}