{"id":"20188","vid":"3389","title":"超时空之钥","sub":"クロノ·トリガー","length":13,"score":9.4,"count":308,"platform":[{"label":"PC","cn":false},{"label":"iOS","cn":false},{"label":"Android","cn":false},{"label":"PSV","cn":false},{"label":"PS3","cn":false},{"label":"Wii","cn":false},{"label":"PSP","cn":false},{"label":"NDS","cn":false},{"label":"PS","cn":false},{"label":"SFC","cn":false}],"date":["最早发售 1995-03-11"],"tags":["角色扮演"],"desc":"本作的 SFC 版发售与 1995 年 3 月 11 日，在经过 PS 版的重制后终于在 NDS 上再次登场。和初版相比，游戏的主线剧情并没有发生变化，只是在特定的剧情中加入了重新制作的动画，而让人称道的游戏配乐则仍是由 SFC 版主要负责音乐的光田康来进行重新编曲和混音，让老玩家也有耳目一新的感觉。","dev":["Square Enix"],"pub":["Square Enix"]}