{"id":"283554","vid":"11422","title":"使命召唤 现代战争","sub":"Call of Duty: Modern Warfare","length":7,"score":8.5,"count":580,"platform":[{"label":"PS4","cn":true},{"label":"XB1","cn":true},{"label":"PC","cn":true}],"date":[["最早发售 2019-10-25","中文发售 2019-10-25"],["最早发售 2019-10-25","中文发售 2019-10-25"],["最早发售 2019-10-25","中文发售 2019-10-25"],["最早发售 2019-10-25","中文发售 2019-10-25"]],"tags":["主视角","射击","竞技"],"desc":"《使命召唤 现代战争》作为重启作，将讲述玩家熟悉的普莱斯队长的故事。玩家将扮演多位顶尖的特战队员，执行生死一线的绝密任务，颠覆世界大国间的微妙平衡。玩家将与不同的国际特种部队和为自由而战的斗士合作，转战于战争的灰色地带。任务将包括潜入、近距作战（Close Quarters）及远程作战，这将考验玩家对于战术的选择。值得注意的是，《使命召唤 现代战争》将是系列首个支持主机和 PC 跨平台联机的作品。游戏不会推出季票内容，以确保玩家群体不会因为付费地图等内容被分割。本作将使用全新的引擎进行开发，而全新的引擎将为游戏的画面、运行带来新的突破。","dev":["Infinity Ward"],"pub":["Activision"]}