{"id":"642","vid":"478","title":"鬼泣4","sub":"Devil May Cry 4","length":"5","score":8.6,"count":1227,"platform":[{"label":"PC","cn":true},{"label":"iOS","cn":false},{"label":"Android","cn":false},{"label":"PS3","cn":false},{"label":"X360","cn":false}],"date":[["最早发售 2008-07-08","中文发售 2019-03-28"],["最早发售 2011-02-03"],["最早发售 2011-02-03"],["最早发售 2008-01-31"],["最早发售 2008-01-31"],["最早发售 2008-01-31","中文发售 2019-03-28"]],"tags":["动作"],"desc":"这是 3D 动作游戏名门《鬼泣》系列步入次世代的第一作，发售前便极受关注。4 代首次采用跨平台战略，销量也因此轻松突破 200 万。游戏的画面、音效等传统指标都比较过硬，系统方面有传承也有创新，具有比较高的研究价值。新主角尼禄的形象和性格都有但丁的影子，但因为 EX 技和恶魔之手的存在，令其操作手感与但丁大相径庭，战斗也更趋向于表演性。游戏流程共分 20 关，其中有 7 关的流程是操控但丁来完成的，有一些原路返回和重复的 BOSS 战受到了玩家的非议，不过打法方面因为与尼禄差别比较大，也让不少玩家重温了原汁原味的《鬼泣》，而巅峰级的手感和打击感让玩家获得了更为兴奋的体验。","lang":["简中"],"dev":["CAPCOM"],"pub":["CAPCOM"]}